fastapi_helper/__init__.py
fastapi_helper/client/__init__.py
fastapi_helper/client/app.py
fastapi_helper/client/middleware.py
fastapi_helper/client/admin/__init__.py
fastapi_helper/client/admin/views.py
fastapi_helper/client/frontend/index.html
fastapi_helper/client/frontend/panel.html
fastapi_helper/client/frontend/css/panel.css
fastapi_helper/client/frontend/css/styles.css
fastapi_helper/client/frontend/js/app.js
fastapi_helper/client/frontend/js/panel.js
fastapi_helper/pj/__init__.py
fastapi_helper/pj/gpt_v1/__init__.py
fastapi_helper/pj/gpt_v1/enums.py
fastapi_helper/pj/gpt_v1/gpt_app.py
fastapi_helper/pj/gpt_v1/lifespan.py
fastapi_helper/pj/gpt_v1/router.py
fastapi_helper/pj/gpt_v1/schema.py
fastapi_helper/pj/gpt_v1/settings.py
fastapi_helper/pj/gpt_v1/types.py
fastapi_helper/sql/__init__.py
fastapi_helper/sql/base.py
fastapi_helper/sql/db_helper.py
fastapi_helper/sql/models.py
fastapi_all_helper-0.170.0.dist-info/METADATA
fastapi_all_helper-0.170.0.dist-info/WHEEL
fastapi_all_helper-0.170.0.dist-info/licenses/LICENSE
fastapi_all_helper-0.170.0.dist-info/RECORD
