Metadata-Version: 2.4
Name: fastapi-all-helper
Version: 0.170.0
Summary: Helper classes and utilities for FastAPI and SQLAlchemy
Project-URL: Homepage, https://github.com/neforceo/fastapi-helper-
Project-URL: Repository, https://github.com/neforceo/fastapi-helper-
Project-URL: Issues, https://github.com/neforceo/fastapi-helper/issues-
Author-email: NEFOR <n7for8572@gmail.com>
License: MIT License
License-File: LICENSE
Classifier: Development Status :: 4 - Beta
Classifier: Intended Audience :: Developers
Classifier: License :: OSI Approved :: MIT License
Classifier: Programming Language :: Python :: 3
Classifier: Programming Language :: Python :: 3.10
Classifier: Programming Language :: Python :: 3.11
Classifier: Programming Language :: Python :: 3.12
Classifier: Topic :: Internet :: WWW/HTTP
Classifier: Topic :: Software Development :: Libraries :: Python Modules
Requires-Python: >=3.10
Requires-Dist: aiosqlite>=0.22.1
Requires-Dist: fastapi>=0.128.0
Requires-Dist: g4f>=6.7.5
Requires-Dist: httpx>=0.28.1
Requires-Dist: pydantic-settings>=2.12.0
Requires-Dist: python-multipart>=0.0.21
Requires-Dist: sqlalchemy>=2.0.45
Requires-Dist: uvicorn>=0.40.0
Provides-Extra: dev
Requires-Dist: black>=23.0.0; extra == 'dev'
Requires-Dist: flake8>=6.0.0; extra == 'dev'
Requires-Dist: isort>=5.0.0; extra == 'dev'
Requires-Dist: pytest-asyncio>=0.21.0; extra == 'dev'
Requires-Dist: pytest>=7.0.0; extra == 'dev'
